{"nodes": [{"id": "template_prompt_adhoc", "label": "PROMPT_ADHOC.md \u2014 Ad-hoc Task Mode Instructions", "file_type": "document", "source_file": "templates/PROMPT_ADHOC.md", "source_location": null, "source_url": null, "captured_at": null, "author": null, "contributor": null}, {"id": "adhoc_task_id_format", "label": "Ad-hoc Task ID Format (AHXX) \u2014 Task Reference System", "file_type": "document", "source_file": "templates/PROMPT_ADHOC.md", "source_location": "Task ID Assignment", "source_url": null, "captured_at": null, "author": null, "contributor": null}], "edges": [{"source": "template_prompt_adhoc", "target": "ralph_status_block", "relation": "references", "confidence": "EXTRACTED", "confidence_score": 1.0, "source_file": "templates/PROMPT_ADHOC.md", "source_location": "Status Reporting", "weight": 1.0}, {"source": "template_prompt_adhoc", "target": "adhoc_task_id_format", "relation": "references", "confidence": "EXTRACTED", "confidence_score": 1.0, "source_file": "templates/PROMPT_ADHOC.md", "source_location": "Task ID Assignment", "weight": 1.0}, {"source": "template_prompt_adhoc", "target": "ralph_files_fix_plan_md", "relation": "references", "confidence": "EXTRACTED", "confidence_score": 1.0, "source_file": "templates/PROMPT_ADHOC.md", "source_location": "Your Mission", "weight": 1.0}, {"source": "template_prompt_adhoc", "target": "template_prompt_compress", "relation": "semantically_similar_to", "confidence": "INFERRED", "confidence_score": 0.72, "source_file": "templates/PROMPT_ADHOC.md", "source_location": null, "weight": 0.72}], "hyperedges": []}